solar/__init__.py
solar/_fake.py
solar/_version.py
solar/colina.py
solar/kurucz.py
solar/rieke.py
solar/stis.py
solar/stis_rieke.py
solar/data_files/kurucz-fsunallp.2000resam125.txt
solar/data_files/rieke-solar_spec.fits
solar/data_files/stis-sun_reference_stis_002.fits
rms_solar-2.0.3.dist-info/LICENSE
rms_solar-2.0.3.dist-info/METADATA
rms_solar-2.0.3.dist-info/WHEEL
rms_solar-2.0.3.dist-info/top_level.txt
rms_solar-2.0.3.dist-info/RECORD
