Metadata-Version: 2.1
Name: rms-solar
Version: 2.0.3
Summary: Models for solar flux density at 1 AU
Maintainer-email: "Robert S. French" <rfrench@seti.org>
License: Apache-2.0
Project-URL: Homepage, https://github.com/SETI/rms-solar
Project-URL: Documentation, https://rms-solar.readthedocs.io/en/latest
Project-URL: Repository, https://github.com/SETI/rms-solar
Project-URL: Source, https://github.com/SETI/rms-solar
Project-URL: Issues, https://github.com/SETI/rms-solar/issues
Keywords: solar,flux
Classifier: Development Status :: 5 - Production/Stable
Classifier: Natural Language :: English
Classifier: Topic :: Scientific/Engineering
Classifier: Topic :: Scientific/Engineering :: Astronomy
Classifier: Topic :: Software Development :: Libraries :: Python Modules
Classifier: Topic :: Utilities
Classifier: License :: OSI Approved :: Apache Software License
Classifier: Programming Language :: Python :: 3.8
Classifier: Programming Language :: Python :: 3.9
Classifier: Programming Language :: Python :: 3.10
Classifier: Programming Language :: Python :: 3.11
Classifier: Programming Language :: Python :: 3.12
Classifier: Programming Language :: Python :: 3.13
Classifier: Operating System :: MacOS :: MacOS X
Classifier: Operating System :: POSIX :: Linux
Classifier: Operating System :: Microsoft :: Windows
Requires-Python: >=3.8
License-File: LICENSE
Requires-Dist: astropy
Requires-Dist: numpy
Requires-Dist: rms-tabulation
